{
  "gameMode": "master",
  "difficulty": 4,
  "elapsedSeconds": 119,
  "currentScore": 0,
  "imageSource": "assets/images/default_puzzle.jpg",
  "placedPiecesIds": [],
  "availablePiecesIds": [],
  "masterPieces": [
    {
      "nodeId": 0,
      "positionX": 62.063472808707246,
      "positionY": 40.11260953193471,
      "scale": 0.5,
      "rotation": 0.0,
      "group": 0
    },
    {
      "nodeId": 1,
      "positionX": 198.06347280870725,
      "positionY": 40.11260953193471,
      "scale": 0.5,
      "rotation": 0.0,
      "group": 0
    },
    {
      "nodeId": 2,
      "positionX": 356.73047553033757,
      "positionY": 241.83229835380564,
      "scale": 0.5,
      "rotation": 4.710831654150164,
      "group": 2
    },
    {
      "nodeId": 3,
      "positionX": 62.063472808707246,
      "positionY": 176.1126095319347,
      "scale": 0.5,
      "rotation": 0.0,
      "group": 0
    },
    {
      "nodeId": 4,
      "positionX": 198.06347280870725,
      "positionY": 176.1126095319347,
      "scale": 0.5,
      "rotation": 0.0,
      "group": 0
    },
    {
      "nodeId": 5,
      "positionX": 388.98317943624596,
      "positionY": 669.6530491121258,
      "scale": 0.5,
      "rotation": 4.7142147629636995,
      "group": 5
    },
    {
      "nodeId": 6,
      "positionX": 385.75652137809885,
      "positionY": 314.7974818025576,
      "scale": 0.5,
      "rotation": 0.2488568767897825,
      "group": 6
    },
    {
      "nodeId": 7,
      "positionX": 363.8039655366739,
      "positionY": 525.2374298749872,
      "scale": 0.5,
      "rotation": 4.979984966470551,
      "group": 7
    },
    {
      "nodeId": 8,
      "positionX": 72.21056302351695,
      "positionY": 414.9835029741695,
      "scale": 0.5,
      "rotation": 3.141592653589793,
      "group": 8
    }
  ],
  "user_id": 2,
  "saved_at": "2025-09-08T15:20:44.573699"
}